no_nonsense/__init__.py
no_nonsense/no_nonsense.py
no_nonsense-0.0.4.dist-info/METADATA
no_nonsense-0.0.4.dist-info/WHEEL
no_nonsense-0.0.4.dist-info/entry_points.txt
no_nonsense-0.0.4.dist-info/licenses/LICENSE
no_nonsense-0.0.4.dist-info/RECORD
