Metadata-Version: 2.3
Name: no_nonsense
Version: 0.0.4
Summary: No nonsense is a static site generator.
Project-URL: Homepage, https://gitlab.com/rahem027/no_nonsense
Project-URL: Issues, https://gitlab.com/rahem027/no_nonsense/-/issues
Author-email: Hemil Ruparel <hemilruparel2002@gmail.com>
License-File: LICENSE
Classifier: Development Status :: 3 - Alpha
Classifier: Intended Audience :: Developers
Classifier: License :: OSI Approved :: MIT License
Classifier: Operating System :: OS Independent
Classifier: Programming Language :: Python :: 3
Requires-Python: >=3.8
Requires-Dist: ruamel-yaml-clib==0.2.8
Requires-Dist: ruamel-yaml==0.18.6
Requires-Dist: wheezy-template==3.2.2
